LICENSE
MANIFEST.in
setup.py
MyKeys.egg-info/PKG-INFO
MyKeys.egg-info/SOURCES.txt
MyKeys.egg-info/dependency_links.txt
MyKeys.egg-info/entry_points.txt
MyKeys.egg-info/top_level.txt
mykeys/__init__.py
mykeys/cmdline.py
mykeys/keyfile.py
mykeys/keys.py
mykeys/data/keyfile
test/test_mykeys.py