Metadata-Version: 1.1
Name: MyKeys
Version: 0.1
Summary: Key/secret provider
Home-page: http://github.com/vladris/mykeys
Author: Vlad Riscutia
Author-email: riscutiavlad@gmail.com
License: FreeBSD
Download-URL: http://pypi.python.org/pypi/MyKeys
Platform: any
Classifier: Development Status :: 4 - Beta
Classifier: Environment :: Console
Classifier: Intended Audience :: End Users/Desktop
Classifier: License :: OSI Approved :: BSD License
Classifier: Operating System :: OS Independent
Classifier: Programming Language :: Python
